influxdb_client-stubs/METADATA.toml
influxdb_client-stubs/__init__.pyi
influxdb_client-stubs/configuration.pyi
influxdb_client-stubs/extras.pyi
influxdb_client-stubs/py.typed
influxdb_client-stubs/rest.pyi
influxdb_client-stubs/version.pyi
influxdb_client-stubs/_async/__init__.pyi
influxdb_client-stubs/_async/api_client.pyi
influxdb_client-stubs/_async/rest.pyi
influxdb_client-stubs/_sync/__init__.pyi
influxdb_client-stubs/_sync/api_client.pyi
influxdb_client-stubs/_sync/rest.pyi
influxdb_client-stubs/client/__init__.pyi
influxdb_client-stubs/client/_base.pyi
influxdb_client-stubs/client/_pages.pyi
influxdb_client-stubs/client/authorizations_api.pyi
influxdb_client-stubs/client/bucket_api.pyi
influxdb_client-stubs/client/delete_api.pyi
influxdb_client-stubs/client/delete_api_async.pyi
influxdb_client-stubs/client/exceptions.pyi
influxdb_client-stubs/client/flux_csv_parser.pyi
influxdb_client-stubs/client/flux_table.pyi
influxdb_client-stubs/client/influxdb_client.pyi
influxdb_client-stubs/client/influxdb_client_async.pyi
influxdb_client-stubs/client/invokable_scripts_api.pyi
influxdb_client-stubs/client/labels_api.pyi
influxdb_client-stubs/client/logging_handler.pyi
influxdb_client-stubs/client/organizations_api.pyi
influxdb_client-stubs/client/query_api.pyi
influxdb_client-stubs/client/query_api_async.pyi
influxdb_client-stubs/client/tasks_api.pyi
influxdb_client-stubs/client/users_api.pyi
influxdb_client-stubs/client/warnings.pyi
influxdb_client-stubs/client/write_api.pyi
influxdb_client-stubs/client/write_api_async.pyi
influxdb_client-stubs/client/util/__init__.pyi
influxdb_client-stubs/client/util/date_utils.pyi
influxdb_client-stubs/client/util/date_utils_pandas.pyi
influxdb_client-stubs/client/util/helpers.pyi
influxdb_client-stubs/client/util/multiprocessing_helper.pyi
influxdb_client-stubs/client/write/__init__.pyi
influxdb_client-stubs/client/write/dataframe_serializer.pyi
influxdb_client-stubs/client/write/point.pyi
types_influxdb_client-1.45.0.20241221.dist-info/LICENSE
types_influxdb_client-1.45.0.20241221.dist-info/METADATA
types_influxdb_client-1.45.0.20241221.dist-info/WHEEL
types_influxdb_client-1.45.0.20241221.dist-info/top_level.txt
types_influxdb_client-1.45.0.20241221.dist-info/RECORD
